[{
 "type":
 "wienerschnitzler",
 "color":
 "#ECDA98",
 "caption":
 "Wiener Schnitzler",
 "head":
 "Lienz"
}, {
 "type":
 "wienerschnitzler",
 "color":
 "#ECDA98",
 "caption":
 "Wiener Schnitzler",
 "head":
 "Villach",
 "desc":
{"listPlace":
  [
 {
 "placeName":
 "Villach Hauptbahnhof",
 "ref":
 ""}
 ]
}
}, {
 "type":
 "wienerschnitzler",
 "color":
 "#ECDA98",
 "caption":
 "Wiener Schnitzler",
 "head":
 "Klagenfurt",
 "desc":
{"listPlace":
  [
 {
 "placeName":
 "Klagenfurt Hauptbahnhof",
 "ref":
 ""}
 ]
}
}] 