[{
 "type":
 "wienerschnitzler",
 "color":
 "#ECDA98",
 "caption":
 "Wiener Schnitzler",
 "head":
 "Wien",
 "desc":
{"listPlace":
  [
 {
 "placeName":
 "I., Innere Stadt",
 "ref":
 ""}
 ]
}
}, {
 "type":
 "schnitzler-events",
 "color":
 "#9BC53D",
 "filename":
 "entity/207374/",
 "caption":
 "Ereignisse in der PMB",
 "idno":
 "https://pmb.acdh.oeaw.ac.at/entity/207374/",
 "head":
 "Aufführung von Hamlet, 6.12.1876",
 "desc":
{"listBibl":
  [
 {
 "title":
 "Hamlet",
 "ref":
 ""}
 ],
 "listPerson":
  [
{
 "persName":
 "Arthur Schnitzler",
 "ref":
 ""}],
 "listPlace":
  [
 {
 "placeName":
 "Ronacher",
 "ref":
 ""}
 ]
}
}] 