[{
 "type":
 "schnitzler-orte",
 "color":
 "#045344",
 "filename":
 "entity/118/",
 "caption":
 "Aufenthaltsorte",
 "idno":
 "https://pmb.acdh.oeaw.ac.at/entity/118/",
 "head":
 "Carl-Theater"
}, {
 "type":
 "pmb",
 "color":
 "#9B5F98",
 "filename":
 "entity/207378/",
 "caption":
 "PMB",
 "idno":
 "https://pmb.acdh.oeaw.ac.at/entity/207378/",
 "head":
 "Konzert im Carl-Theater, 24.1.1877",
 "desc":
{"listOrg":
  [
 {
 "orgName":
 "Carl-Theater",
 "ref":
 ""}
 ],
 "listPerson":
  [
{
 "persName":
 "Christina Nilsson",
 "ref":
 ""},
 {
 "persName":
 "Arthur Schnitzler",
 "ref":
 ""}],
 "listPlace":
  [
 {
 "placeName":
 "Carl-Theater",
 "ref":
 ""}
 ]
}
}, {
 "type":
 "schnitzler-chronik-manuell",
 "filename":
 "1428639_0070",
 "idno":
 "https://schnitzler-mikrofilme.acdh.oeaw.ac.at/1428639_0070.html",
 "head":
 "Mappe A160 – Datumsangabe auf Blatt von Akademische Herzen: »Fünftes Kapitel.«"
}] 