[{
 "type":
 "schnitzler-tagebuch",
 "color":
 "#037a33",
 "filename":
 "entry__1879-08-30",
 "caption":
 "Tagebuch",
 "idno":
 "https://schnitzler-tagebuch.acdh.oeaw.ac.at/entry__1879-08-30.html",
 "head":
 "Tagebuch, 30. August 1879",
 "desc":
{"listPlace":
  [
 {
 "placeName":
 "Wien",
 "ref":
 "pmb50"}
 ,  {
 "placeName":
 "Frankfurt am Main",
 "ref":
 "pmb146"}
 ]
}
}, {
 "type":
 "URL",
 "subtype":
 "wienerschnitzler",
 "head":
 "Wien",
 "desc":
{"listPlace":
  [
 {
 "placeName":
 "I., Innere Stadt",
 "ref":
 ""}
 ]
}
}, {
 "type":
 "URL",
 "subtype":
 "wienerschnitzler",
 "head":
 "Frankfurt am Main"
}] 