[{
 "type":
 "wienerschnitzler",
 "color":
 "#6F5106",
 "caption":
 "Wiener Schnitzler",
 "idno":
 "https://wienerschnitzler.org/tag.html#1879-11-14",
 "head":
 "Wien",
 "desc":
{"listPlace":
  [
 {
 "placeName":
 "I., Innere Stadt",
 "ref":
 ""}
 ]
}
}, {
 "type":
 "URL",
 "subtype":
 "pmb",
 "filename":
 "entity/207524/",
 "idno":
 "https://pmb.acdh.oeaw.ac.at/entity/207524/",
 "head":
 "Aufführung von Haus Fourchambault, 14.11.1879",
 "desc":
{"listBibl":
  [
 {
 "title":
 "Haus Fourchambault",
 "ref":
 ""}
 ],
 "listPerson":
  [
{
 "persName":
 "Arthur Schnitzler",
 "ref":
 ""}],
 "listPlace":
  [
 {
 "placeName":
 "Ronacher",
 "ref":
 ""}
 ]
}
}] 