[{
 "type":
 "schnitzler-tagebuch",
 "color":
 "#037a33",
 "filename":
 "entry__1881-03-05",
 "caption":
 "Tagebuch",
 "idno":
 "https://schnitzler-tagebuch.acdh.oeaw.ac.at/entry__1881-03-05.html",
 "head":
 "Tagebuch, 5. März 1881",
 "desc":
{"listPerson":
  [
{
 "persName":
 "Maximilian Bern",
 "ref":
 "person_13660"},
 {
 "persName":
 "Hermann Löbel",
 "ref":
 "person_17613"},
 {
 "persName":
 "Jacques Pichler",
 "ref":
 "person_18766"},
 {
 "persName":
 "Karl Zucker",
 "ref":
 "person_21591"},
 {
 "persName":
 "Franziska Mütter",
 "ref":
 "person_18320"}],
 "listBibl":
  [
 {
 "title":
 "Aus der Mode",
 "ref":
 "pmb30919"}
 ]
}
}, {
 "type":
 "wienerschnitzler",
 "color":
 "#6F5106",
 "caption":
 "Wiener Schnitzler",
 "idno":
 "https://wienerschnitzler.org/tag.html#1881-03-05",
 "head":
 "Wien",
 "desc":
{"listPlace":
  [
 {
 "placeName":
 "I., Innere Stadt",
 "ref":
 ""}
 ]
}
}, {
 "type":
 "URL",
 "subtype":
 "schnitzler-kultur",
 "filename":
 "pmb207670",
 "idno":
 "https://schnitzler-kultur.acdh.oeaw.ac.at/pmb207670.html",
 "head":
 "Hausball bei Julius Schlesinger, 5.3.1881",
 "desc":
{"listPerson":
  [
{
 "persName":
 "Arthur Schnitzler",
 "ref":
 ""},
 {
 "persName":
 "Julius Schlesinger",
 "ref":
 ""}],
 "listPlace":
  [
 {
 "placeName":
 "Opernring 11",
 "ref":
 ""}
 ]
}
}, {
 "type":
 "URL",
 "subtype":
 "schnitzler-kultur",
 "filename":
 "pmb207669",
 "idno":
 "https://schnitzler-kultur.acdh.oeaw.ac.at/pmb207669.html",
 "head":
 "Premiere von Noble Bekanntschaft, 5.3.1881",
 "desc":
{"listBibl":
  [
 {
 "title":
 "Noble Bekanntschaft",
 "ref":
 ""}
 ],
 "listPerson":
  [
{
 "persName":
 "Arthur Schnitzler",
 "ref":
 ""}],
 "listPlace":
  [
 {
 "placeName":
 "Ronacher",
 "ref":
 ""}
 ]
}
}] 