[{
 "type":
 "wienerschnitzler",
 "color":
 "#6F5106",
 "caption":
 "Wiener Schnitzler",
 "idno":
 "https://wienerschnitzler.org/tag.html#1881-03-08",
 "head":
 "Wien",
 "desc":
{"listPlace":
  [
 {
 "placeName":
 "I., Innere Stadt",
 "ref":
 ""}
 ]
}
}, {
 "type":
 "schnitzler-kultur",
 "color":
 "#6B4C5A",
 "filename":
 "pmb207673",
 "caption":
 "Kulturveranstaltungen",
 "idno":
 "https://schnitzler-kultur.acdh.oeaw.ac.at/pmb207673.html",
 "head":
 "Aufführung von Oidípous Týrannos, 8.3.1881",
 "desc":
{"listBibl":
  [
 {
 "title":
 "Oidípous Týrannos",
 "ref":
 ""}
 ],
 "listPerson":
  [
{
 "persName":
 "Richard Türschmann",
 "ref":
 ""},
 {
 "persName":
 "Arthur Schnitzler",
 "ref":
 ""}],
 "listPlace":
  [
 {
 "placeName":
 "Bösendorfer-Saal",
 "ref":
 ""}
 ]
}
}] 