[{
 "type":
 "wienerschnitzler",
 "color":
 "#ECDA98",
 "caption":
 "Wiener Schnitzler",
 "head":
 "Wien",
 "desc":
{"listPlace":
  [
 {
 "placeName":
 "I., Innere Stadt",
 "ref":
 ""}
 ]
}
}, {
 "type":
 "schnitzler-events",
 "color":
 "#9BC53D",
 "filename":
 "entity/207957/",
 "caption":
 "Ereignisse in der PMB",
 "idno":
 "https://pmb.acdh.oeaw.ac.at/entity/207957/",
 "head":
 "Aufführung von Tannhäuser und der Sängerkrieg, 25.10.1885",
 "desc":
{"listOrg":
  [
 {
 "orgName":
 "K.K. Hof-Oper",
 "ref":
 ""}
 ],
 "listBibl":
  [
 {
 "title":
 "Tannhäuser und der Sängerkrieg auf Wartburg",
 "ref":
 ""}
 ],
 "listPerson":
  [
{
 "persName":
 "Arthur Schnitzler",
 "ref":
 ""}],
 "listPlace":
  [
 {
 "placeName":
 "Oper",
 "ref":
 ""}
 ]
}
}] 