[{
 "type":
 "schnitzler-orte",
 "color":
 "#045344",
 "filename":
 "entity/50/",
 "caption":
 "Aufenthaltsorte",
 "idno":
 "https://pmb.acdh.oeaw.ac.at/entity/50/",
 "head":
 "Wien"
}, {
 "type":
 "schnitzler-orte",
 "color":
 "#045344",
 "filename":
 "entity/796/",
 "caption":
 "Aufenthaltsorte",
 "idno":
 "https://pmb.acdh.oeaw.ac.at/entity/796/",
 "head":
 "Thalhof"
}, {
 "type":
 "schnitzler-orte",
 "color":
 "#045344",
 "filename":
 "entity/185621/",
 "caption":
 "Aufenthaltsorte",
 "idno":
 "https://pmb.acdh.oeaw.ac.at/entity/185621/",
 "head":
 "Burgtheater [Altes Burgtheater]"
}, {
 "type":
 "pmb",
 "color":
 "#9B5F98",
 "filename":
 "entity/208041/",
 "caption":
 "PMB",
 "idno":
 "https://pmb.acdh.oeaw.ac.at/entity/208041/",
 "head":
 "Aufführung von Die alten Junggesellen, 14.6.1886",
 "desc":
{"listOrg":
  [
 {
 "orgName":
 "Burgtheater",
 "ref":
 ""}
 ],
 "listBibl":
  [
 {
 "title":
 "Die alten Junggesellen. Pariser Sittengemälde in 5 Aufzügen",
 "ref":
 ""}
 ],
 "listPerson":
  [
{
 "persName":
 "Arthur Schnitzler",
 "ref":
 ""}],
 "listPlace":
  [
 {
 "placeName":
 "Burgtheater [Altes Burgtheater]",
 "ref":
 ""}
 ]
}
}] 