[{
 "type":
 "schnitzler-orte",
 "color":
 "#045344",
 "filename":
 "entity/50/",
 "caption":
 "Aufenthaltsorte",
 "idno":
 "https://pmb.acdh.oeaw.ac.at/entity/50/",
 "head":
 "Wien"
}, {
 "type":
 "schnitzler-orte",
 "color":
 "#045344",
 "filename":
 "entity/185621/",
 "caption":
 "Aufenthaltsorte",
 "idno":
 "https://pmb.acdh.oeaw.ac.at/entity/185621/",
 "head":
 "Burgtheater [Altes Burgtheater]"
}, {
 "type":
 "schnitzler-events",
 "color":
 "#9BC53D",
 "filename":
 "entity/208163/",
 "caption":
 "Ereignisse in der PMB",
 "idno":
 "https://pmb.acdh.oeaw.ac.at/entity/208163/",
 "head":
 "Aufführung von Goldfische, 30.9.1887",
 "desc":
{"listOrg":
  [
 {
 "orgName":
 "Burgtheater",
 "ref":
 ""}
 ],
 "listBibl":
  [
 {
 "title":
 "Goldfische",
 "ref":
 ""}
 ],
 "listPerson":
  [
{
 "persName":
 "Arthur Schnitzler",
 "ref":
 ""}],
 "listPlace":
  [
 {
 "placeName":
 "Burgtheater [Altes Burgtheater]",
 "ref":
 ""}
 ]
}
}] 