[{
 "type":
 "schnitzler-tagebuch",
 "color":
 "#037a33",
 "filename":
 "entry__1888-07-07",
 "caption":
 "Tagebuch",
 "idno":
 "https://schnitzler-tagebuch.acdh.oeaw.ac.at/entry__1888-07-07.html",
 "head":
 "Tagebuch, 7. Juli 1888"
}, {
 "type":
 "wienerschnitzler",
 "color":
 "#ECDA98",
 "caption":
 "Wiener Schnitzler",
 "idno":
 "https://wienerschnitzler.org/tag.html#1888-07-07",
 "head":
 "London",
 "desc":
{"listPlace":
  [
 {
 "placeName":
 "18, Cromwell Place",
 "ref":
 ""}
 ,  {
 "placeName":
 "Alhambra Theatre",
 "ref":
 ""}
 ,  {
 "placeName":
 "London Lock Hospital",
 "ref":
 ""}
 ]
}
}, {
 "type":
 "schnitzler-kultur",
 "color":
 "#6B4C5A",
 "filename":
 "pmb208265",
 "caption":
 "Kulturveranstaltungen",
 "idno":
 "https://schnitzler-kultur.acdh.oeaw.ac.at/pmb208265.html",
 "head":
 "Alhambra Theatre, 7.7.1888",
 "desc":
{"listPerson":
  [
{
 "persName":
 "Arthur Schnitzler",
 "ref":
 ""}],
 "listPlace":
  [
 {
 "placeName":
 "Alhambra Theatre",
 "ref":
 ""}
 ]
}
}] 