[{
 "type":
 "schnitzler-tagebuch",
 "color":
 "#037a33",
 "filename":
 "entry__1890-01-25",
 "caption":
 "Tagebuch",
 "idno":
 "https://schnitzler-tagebuch.acdh.oeaw.ac.at/entry__1890-01-25.html",
 "head":
 "Tagebuch, 25. Januar 1890",
 "desc":
{"listPerson":
  [
{
 "persName":
 "Peter Altenberg",
 "ref":
 "person_13162"},
 {
 "persName":
 "Helene Binder",
 "ref":
 "person_13733"},
 {
 "persName":
 "Marie Glümer",
 "ref":
 "person_15485"},
 {
 "persName":
 "Ludwig Pollak",
 "ref":
 "person_18889"},
 {
 "persName":
 "Alexander von Weilen",
 "ref":
 "person_21157"},
 {
 "persName":
 "Anna Holitscher",
 "ref":
 "person_16321"}]
}
}, {
 "type":
 "schnitzler-orte",
 "color":
 "#045344",
 "caption":
 "Aufenthaltsorte",
 "head":
 "Wien",
 "desc":
{"listPlace":
  [
 {
 "placeName":
 "I., Innere Stadt",
 "ref":
 ""}
 ]
}
}, {
 "type":
 "schnitzler-orte",
 "color":
 "#045344",
 "caption":
 "Aufenthaltsorte",
 "head":
 "Kärntnerring 12/Bösendorferstraße 11 Kärntnerring 12/Bösendorferstraße 11"
}, {
 "type":
 "schnitzler-events",
 "color":
 "#9BC53D",
 "filename":
 "entity/208375/",
 "caption":
 "Ereignisse in der PMB",
 "idno":
 "https://pmb.acdh.oeaw.ac.at/entity/208375/",
 "head":
 "Ball Pollak, 25.1.1890",
 "desc":
{"listPerson":
  [
{
 "persName":
 "Arthur Schnitzler",
 "ref":
 ""}],
 "listPlace":
  [
 {
 "placeName":
 "Opernring",
 "ref":
 ""}
 ]
}
}] 