[{
 "type":
 "schnitzler-tagebuch",
 "color":
 "#037a33",
 "filename":
 "entry__1891-09-02",
 "caption":
 "Tagebuch",
 "idno":
 "https://schnitzler-tagebuch.acdh.oeaw.ac.at/entry__1891-09-02.html",
 "head":
 "Tagebuch, 2. September 1891",
 "desc":
{"listBibl":
  [
 {
 "title":
 "Das letzte Wort",
 "ref":
 "pmb77485"}
 ],
 "listPlace":
  [
 {
 "placeName":
 "Baden bei Wien",
 "ref":
 "pmb662"}
 ]
}
}, {
 "type":
 "schnitzler-briefe",
 "color":
 "#A63437",
 "filename":
 "L03103",
 "caption":
 "Briefe mit Autorinnen und Autoren",
 "idno":
 "https://schnitzler-briefe.acdh.oeaw.ac.at/L03103.html",
 "head":
 "Felix Salten an Arthur Schnitzler, 2. 9. 1891",
 "desc":
{"listPerson":
  [
{
 "persName":
 "Felix Salten",
 "ref":
 "pmb2167"},
 {
 "persName":
 "Arthur Schnitzler",
 "ref":
 "pmb2121"},
 {
 "persName":
 "Felix Salten",
 "ref":
 "pmb2167"},
 {
 "persName":
 "Philipp Salzmann",
 "ref":
 "pmb142892"},
 {
 "persName":
 "Bertha Karlsburg",
 "ref":
 "pmb19143"},
 {
 "persName":
 "Paula Makay",
 "ref":
 "pmb144310"},
 {
 "persName":
 "Michael Emil Salzmann",
 "ref":
 "pmb45493"},
 {
 "persName":
 "Ignaz Salzmann",
 "ref":
 "pmb142919"},
 {
 "persName":
 "Theodor Salzmann",
 "ref":
 "pmb142928"},
 {
 "persName":
 "Geza Sós",
 "ref":
 "pmb23932"}],
 "listPlace":
  [
 {
 "placeName":
 "Miskolc",
 "ref":
 "pmb44142"}
 ,  {
 "placeName":
 "Wien",
 "ref":
 "pmb50"}
 ,  {
 "placeName":
 "Miskolctapolca",
 "ref":
 "pmb143569"}
 ,  {
 "placeName":
 "Ungarn",
 "ref":
 "pmb35512"}
 ,  {
 "placeName":
 "Mödling",
 "ref":
 "pmb968"}
 ],
 "listOrg":
  [
 {
 "orgName":
 "Danzer’s Orpheum",
 "ref":
 "pmb62834"}
 ]
}
}, {
 "type":
 "wienerschnitzler",
 "color":
 "#6F5106",
 "caption":
 "Wiener Schnitzler",
 "idno":
 "https://wienerschnitzler.org/tag.html#1891-09-02",
 "head":
 "Wien",
 "desc":
{"listPlace":
  [
 {
 "placeName":
 "I., Innere Stadt",
 "ref":
 ""}
 ]
}
}, {
 "type":
 "wienerschnitzler",
 "color":
 "#6F5106",
 "caption":
 "Wiener Schnitzler",
 "idno":
 "https://wienerschnitzler.org/tag.html#1891-09-02",
 "head":
 "Baden bei Wien",
 "desc":
{"listPlace":
  [
 {
 "placeName":
 "Arena in Baden",
 "ref":
 ""}
 ]
}
}, {
 "type":
 "URL",
 "subtype":
 "pmb",
 "filename":
 "entity/208494/",
 "idno":
 "https://pmb.acdh.oeaw.ac.at/entity/208494/",
 "head":
 "Aufführung von Das letzte Wort, 2.9.1891",
 "desc":
{"listOrg":
  [
 {
 "orgName":
 "Stadttheater und Arena",
 "ref":
 ""}
 ],
 "listBibl":
  [
 {
 "title":
 "Das letzte Wort",
 "ref":
 ""}
 ],
 "listPerson":
  [
{
 "persName":
 "Marie Glümer",
 "ref":
 ""},
 {
 "persName":
 "Arthur Schnitzler",
 "ref":
 ""}],
 "listPlace":
  [
 {
 "placeName":
 "Arena in Baden",
 "ref":
 ""}
 ]
}
}] 