[{
 "type":
 "schnitzler-tagebuch",
 "color":
 "#037a33",
 "filename":
 "entry__1898-02-02",
 "caption":
 "Tagebuch",
 "idno":
 "https://schnitzler-tagebuch.acdh.oeaw.ac.at/entry__1898-02-02.html",
 "head":
 "Tagebuch, 2. Februar 1898",
 "desc":
{"listPerson":
  [
{
 "persName":
 "Georg Brandes",
 "ref":
 "person_13920"},
 {
 "persName":
 "Max Eugen Burckhard",
 "ref":
 "person_14065"},
 {
 "persName":
 "Marie Glümer",
 "ref":
 "person_15485"},
 {
 "persName":
 "Paul Schlenther",
 "ref":
 "person_19724"},
 {
 "persName":
 "Marie Reinhard",
 "ref":
 "person_19150"}],
 "listPlace":
  [
 {
 "placeName":
 "Sacher",
 "ref":
 "pmb92506"}
 ]
}
}, {
 "type":
 "schnitzler-orte",
 "color":
 "#045344",
 "filename":
 "entity/50/",
 "caption":
 "Aufenthaltsorte",
 "idno":
 "https://pmb.acdh.oeaw.ac.at/entity/50/",
 "head":
 "Wien"
}, {
 "type":
 "schnitzler-orte",
 "color":
 "#045344",
 "filename":
 "entity/29/",
 "caption":
 "Aufenthaltsorte",
 "idno":
 "https://pmb.acdh.oeaw.ac.at/entity/29/",
 "head":
 "Hotel Sacher"
}, {
 "type":
 "schnitzler-orte",
 "color":
 "#045344",
 "filename":
 "entity/14/",
 "caption":
 "Aufenthaltsorte",
 "idno":
 "https://pmb.acdh.oeaw.ac.at/entity/14/",
 "head":
 "Burgtheater"
}, {
 "type":
 "schnitzler-orte",
 "color":
 "#045344",
 "filename":
 "entity/1106/",
 "caption":
 "Aufenthaltsorte",
 "idno":
 "https://pmb.acdh.oeaw.ac.at/entity/1106/",
 "head":
 "Residenzhotel"
}, {
 "type":
 "schnitzler-orte",
 "color":
 "#045344",
 "filename":
 "entity/200410/",
 "caption":
 "Aufenthaltsorte",
 "idno":
 "https://pmb.acdh.oeaw.ac.at/entity/200410/",
 "head":
 "Heinestraße 36"
}, {
 "type":
 "schnitzler-events",
 "color":
 "#9BC53D",
 "filename":
 "entity/208998/",
 "caption":
 "Ereignisse in der PMB",
 "idno":
 "https://pmb.acdh.oeaw.ac.at/entity/208998/",
 "head":
 "Aufführung von Adrienne Lecouvreur, 2.2.1898",
 "desc":
{"listOrg":
  [
 {
 "orgName":
 "Burgtheater",
 "ref":
 ""}
 ],
 "listBibl":
  [
 {
 "title":
 "Adrienne Lecouvreur",
 "ref":
 ""}
 ],
 "listPerson":
  [
{
 "persName":
 "Arthur Schnitzler",
 "ref":
 ""}],
 "listPlace":
  [
 {
 "placeName":
 "Burgtheater",
 "ref":
 ""}
 ]
}
}, {
 "type":
 "schnitzler-events",
 "color":
 "#9BC53D",
 "filename":
 "entity/200606/",
 "caption":
 "Ereignisse in der PMB",
 "idno":
 "https://pmb.acdh.oeaw.ac.at/entity/200606/",
 "head":
 "Bankett für Max Burckhard, 2.2.1898",
 "desc":
{"listPerson":
  [
{
 "persName":
 "Max Eugen Burckhard",
 "ref":
 ""},
 {
 "persName":
 "Hermann Bahr",
 "ref":
 ""},
 {
 "persName":
 "Arthur Schnitzler",
 "ref":
 ""},
 {
 "persName":
 "Ludwig Speidel",
 "ref":
 ""},
 {
 "persName":
 "Ferdinand Gross",
 "ref":
 ""},
 {
 "persName":
 "Ferdinand von Saar",
 "ref":
 ""},
 {
 "persName":
 "Marcell von Frydmann-Prawy",
 "ref":
 ""},
 {
 "persName":
 "Karl Glossy",
 "ref":
 ""},
 {
 "persName":
 "Julius Bauer",
 "ref":
 ""},
 {
 "persName":
 "Franz von Jauner",
 "ref":
 ""},
 {
 "persName":
 "Ernst Gettke",
 "ref":
 ""},
 {
 "persName":
 "Alfred Grünfeld",
 "ref":
 ""},
 {
 "persName":
 "Leo Ebermann",
 "ref":
 ""},
 {
 "persName":
 "Alexander Girardi",
 "ref":
 ""},
 {
 "persName":
 "Philipp Langmann",
 "ref":
 ""},
 {
 "persName":
 "Victor Kutschera",
 "ref":
 ""},
 {
 "persName":
 "Leopold Kramer",
 "ref":
 ""},
 {
 "persName":
 "August Fournier",
 "ref":
 ""},
 {
 "persName":
 "Gustav Klimt",
 "ref":
 ""},
 {
 "persName":
 "Leonhard Fanto",
 "ref":
 ""},
 {
 "persName":
 "Oscar Hofmann",
 "ref":
 ""},
 {
 "persName":
 "Richard Fellner",
 "ref":
 ""},
 {
 "persName":
 "Hugo Wittmann",
 "ref":
 ""}],
 "listPlace":
  [
 {
 "placeName":
 "Hotel Sacher",
 "ref":
 ""}
 ]
}
}, {
 "type":
 "schnitzler-cmif",
 "subtype":
 "#y8d39a2f-76d4-4426-8799-986c8bf5bc60",
 "color":
 "#654321",
 "caption":
 "Gedruckte Briefwechsel",
 "head":
 "Samuel Fischer an Arthur Schnitzler, 2.2.1898",
 "source":
 "Samuel Fischer, Hedwig Fischer: Briefwechsel mit Autoren. S. Fischer Verlag, Frankfurt am Main: 1989. (nur Korrespondenz mit Arthur Schnitzler)"
}, {
 "type":
 "schnitzler-cmif",
 "subtype":
 "#ya489e21-54d5-40de-a56d-f4548e894428",
 "color":
 "#654321",
 "caption":
 "Gedruckte Briefwechsel",
 "head":
 "Otto Brahm an Arthur Schnitzler, nach 2.2.1898 und vor 3.2.1898",
 "source":
 "Der Briefwechsel Arthur Schnitzler – Otto Brahm. Vollständige Ausgabe. Hg., eingel. und erl. von Oskar Seidlin. Tübingen: Niemeyer, 1975."
}, {
 "type":
 "kalliope-verbund",
 "color":
 "#003574",
 "caption":
 "Kalliope Verbundkatalog",
 "idno":
 "http://kalliope-verbund.info/DE-2498-HS00070924",
 "head":
 "Naschauer, Paul an Schnitzler, Arthur [Briefe]",
 "text":
 "1 Bl."
}] 