[{
 "type":
 "schnitzler-orte",
 "idno":
 "https://pmb.acdh.oeaw.ac.at/entity/50/",
 "head":
 "Wien"
}, {
 "type":
 "schnitzler-tagebuch",
 "idno":
 "https://schnitzler-tagebuch.acdh.oeaw.ac.at/entry__1900-10-26.html",
 "head":
 "Tagebuch, 26. Oktober 1900",
 "desc":
{"listPerson":
  [
{
 "persName":
 "Leopoldine Kirchrath",
 "ref":
 "person_16850"},
 {
 "persName":
 "Albert Speyer",
 "ref":
 "person_20247"},
 {
 "persName":
 "Hermann Speyer",
 "ref":
 "person_20249"},
 {
 "persName":
 "Clara Speyer",
 "ref":
 "person_20248"},
 {
 "persName":
 "Olga Schnitzler",
 "ref":
 "person_19832"}]}

}] 