[{
 "type":
 "schnitzler-tagebuch",
 "color":
 "#037a33",
 "filename":
 "entry__1900-02-28",
 "caption":
 "Tagebuch",
 "idno":
 "https://schnitzler-tagebuch.acdh.oeaw.ac.at/entry__1900-02-28.html",
 "head":
 "Tagebuch, 28. Februar 1900",
 "desc":
{"listPerson":
  [
{
 "persName":
 "Richard Beer-Hofmann",
 "ref":
 "person_13551"},
 {
 "persName":
 "Ludwig Klinenberger",
 "ref":
 "person_16911"},
 {
 "persName":
 "Dora Michaelis",
 "ref":
 "person_18137"},
 {
 "persName":
 "Gustav Schwarzkopf",
 "ref":
 "person_19986"},
 {
 "persName":
 "Hugo von Hofmannsthal",
 "ref":
 "person_16293"}],
 "listPlace":
  [
 {
 "placeName":
 "Edlach",
 "ref":
 "pmb470"}
 ]
}
}, {
 "type":
 "wienerschnitzler",
 "color":
 "#6F5106",
 "caption":
 "Wiener Schnitzler",
 "idno":
 "https://wienerschnitzler.org/tag.html#1900-02-28",
 "head":
 "Edlach",
 "desc":
{"listPlace":
  [
 {
 "placeName":
 "Hotel Edlacherhof",
 "ref":
 ""}
 ]
}
}, {
 "type":
 "wienerschnitzler",
 "color":
 "#6F5106",
 "caption":
 "Wiener Schnitzler",
 "idno":
 "https://wienerschnitzler.org/tag.html#1900-02-28",
 "head":
 "Wien",
 "desc":
{"listPlace":
  [
 {
 "placeName":
 "I., Innere Stadt",
 "ref":
 ""}
 ,  {
 "placeName":
 "IX., Alsergrund",
 "ref":
 ""}
 ]
}
}] 