[{
 "type":
 "schnitzler-tagebuch",
 "color":
 "#037a33",
 "filename":
 "entry__1901-12-08",
 "caption":
 "Tagebuch",
 "idno":
 "https://schnitzler-tagebuch.acdh.oeaw.ac.at/entry__1901-12-08.html",
 "head":
 "Tagebuch, 8. Dezember 1901",
 "desc":
{"listPerson":
  [
{
 "persName":
 "Olga Schnitzler",
 "ref":
 "person_19832"}],
 "listBibl":
  [
 {
 "title":
 "Die Zauberflöte",
 "ref":
 "pmb56668"}
 ],
 "listPlace":
  [
 {
 "placeName":
 "XIX., Döbling",
 "ref":
 "pmb69"}
 ]
}
}, {
 "type":
 "wienerschnitzler",
 "color":
 "#6F5106",
 "caption":
 "Wiener Schnitzler",
 "idno":
 "https://wienerschnitzler.org/tag.html#1901-12-08",
 "head":
 "Wien",
 "desc":
{"listPlace":
  [
 {
 "placeName":
 "I., Innere Stadt",
 "ref":
 ""}
 ,  {
 "placeName":
 "IX., Alsergrund",
 "ref":
 ""}
 ,  {
 "placeName":
 "XIX., Döbling",
 "ref":
 ""}
 ]
}
}, {
 "type":
 "URL",
 "subtype":
 "schnitzler-kultur",
 "filename":
 "pmb209222",
 "idno":
 "https://schnitzler-kultur.acdh.oeaw.ac.at/pmb209222.html",
 "head":
 "Aufführung von Die Zauberflöte, 8.12.1901",
 "desc":
{"listOrg":
  [
 {
 "orgName":
 "K.K. Hof-Oper",
 "ref":
 ""}
 ],
 "listBibl":
  [
 {
 "title":
 "Die Zauberflöte",
 "ref":
 ""}
 ],
 "listPerson":
  [
{
 "persName":
 "Arthur Schnitzler",
 "ref":
 ""}],
 "listPlace":
  [
 {
 "placeName":
 "Oper",
 "ref":
 ""}
 ]
}
}, {
 "type":
 "kalliope-verbund",
 "color":
 "#003574",
 "caption":
 "Kalliope Verbundkatalog",
 "idno":
 "http://kalliope-verbund.info/DE-2498-HS00033022",
 "head":
 "Döring, Carl Wilhelm an Schnitzler, Arthur [Briefe]",
 "text":
 "2 Bl."
}] 