[{
 "type":
 "schnitzler-orte",
 "idno":
 "https://pmb.acdh.oeaw.ac.at/entity/50/",
 "head":
 "Wien"
}, {
 "type":
 "schnitzler-briefe",
 "idno":
 "https://schnitzler-briefe.acdh.oeaw.ac.at/L02634.html",
 "head":
 "Paul Goldmann an Arthur Schnitzler, 26. 4. 1902",
 "desc":
{"listPerson":
  [
{
 "persName":
 "Paul Goldmann",
 "ref":
 "pmb11485"},
 {
 "persName":
 "Josef Kvasnicka",
 "ref":
 "pmb88185"},
 {
 "persName":
 "Karl Strecker",
 "ref":
 "pmb4794"},
 {
 "persName":
 "Ernest von Gréger-Jurco",
 "ref":
 "pmb17461"}],
 "listBibl":
  [
 {
 "title":
 "Ein litterarisch-dramatisches Hochstapler-Stücklein",
 "ref":
 "pmb88182"}
 ,  {
 "title":
 "Die Kinder der Armen",
 "ref":
 "pmb58024"}
 ],
 "listOrg":
  [
 {
 "orgName":
 "Tägliche Rundschau",
 "ref":
 "pmb29691"}
 ,  {
 "orgName":
 "Rose-Theater",
 "ref":
 "pmb88180"}
 ,  {
 "orgName":
 "Berliner Tageblatt",
 "ref":
 "pmb29329"}
 ],
 "listPlace":
  [
 {
 "placeName":
 "Berlin",
 "ref":
 "pmb168"}
 ,  {
 "placeName":
 "Wien",
 "ref":
 "pmb50"}
 ,  {
 "placeName":
 "Frankgasse",
 "ref":
 "pmb397"}
 ,  {
 "placeName":
 "Zimmerstraße",
 "ref":
 "pmb53430"}
 ]}

}, {
 "type":
 "schnitzler-tagebuch",
 "idno":
 "https://schnitzler-tagebuch.acdh.oeaw.ac.at/entry__1902-04-26.html",
 "head":
 "Tagebuch, 26. April 1902",
 "desc":
{"listPerson":
  [
{
 "persName":
 "Paul Goldmann",
 "ref":
 "person_15529"},
 {
 "persName":
 "Ernest von Gréger-Jurco",
 "ref":
 "person_15636"}],
 "listBibl":
  [
 {
 "title":
 "Die Kinder der Armen",
 "ref":
 "pmb58024"}
 ]}

}] 