[{
 "type":
 "schnitzler-tagebuch",
 "color":
 "#037a33",
 "filename":
 "entry__1902-09-12",
 "caption":
 "Tagebuch",
 "idno":
 "https://schnitzler-tagebuch.acdh.oeaw.ac.at/entry__1902-09-12.html",
 "head":
 "Tagebuch, 12. September 1902",
 "desc":
{"listBibl":
  [
 {
 "title":
 "Die griechische Tänzerin. Novellette",
 "ref":
 "pmb30167"}
 ]
}
}, {
 "type":
 "wienerschnitzler",
 "color":
 "#ECDA98",
 "caption":
 "Wiener Schnitzler",
 "idno":
 "https://wienerschnitzler.org/tag.html#1902-09-12",
 "head":
 "Hinterbrühl",
 "desc":
{"listPlace":
  [
 {
 "placeName":
 "Hauptstraße 56",
 "ref":
 ""}
 ]
}
}] 