[{
 "type":
 "schnitzler-tagebuch",
 "color":
 "#037a33",
 "filename":
 "entry__1902-10-28",
 "caption":
 "Tagebuch",
 "idno":
 "https://schnitzler-tagebuch.acdh.oeaw.ac.at/entry__1902-10-28.html",
 "head":
 "Tagebuch, 28. Oktober 1902",
 "desc":
{"listPerson":
  [
{
 "persName":
 "Olga Schnitzler",
 "ref":
 "person_19832"}],
 "listBibl":
  [
 {
 "title":
 "Der Kreuzwegst端rmer",
 "ref":
 "pmb78259"}
 ]
}
}, {
 "type":
 "schnitzler-orte",
 "color":
 "#045344",
 "filename":
 "entity/50/",
 "caption":
 "Aufenthaltsorte",
 "idno":
 "https://pmb.acdh.oeaw.ac.at/entity/50/",
 "head":
 "Wien"
}, {
 "type":
 "schnitzler-orte",
 "color":
 "#045344",
 "filename":
 "entity/77/",
 "caption":
 "Aufenthaltsorte",
 "idno":
 "https://pmb.acdh.oeaw.ac.at/entity/77/",
 "head":
 "Raimund-Theater"
}, {
 "type":
 "schnitzler-orte",
 "color":
 "#045344",
 "filename":
 "entity/438/",
 "caption":
 "Aufenthaltsorte",
 "idno":
 "https://pmb.acdh.oeaw.ac.at/entity/438/",
 "head":
 "Westbahnhof-Restaurant"
}, {
 "type":
 "schnitzler-events",
 "color":
 "#9BC53D",
 "filename":
 "entity/209266/",
 "caption":
 "Ereignisse in der PMB",
 "idno":
 "https://pmb.acdh.oeaw.ac.at/entity/209266/",
 "head":
 "Auff端hrung von Der Kreuzwegst端rmer, 28.10.1902",
 "desc":
{"listOrg":
  [
 {
 "orgName":
 "Raimund-Theater",
 "ref":
 ""}
 ],
 "listBibl":
  [
 {
 "title":
 "Der Kreuzwegst端rmer",
 "ref":
 ""}
 ],
 "listPerson":
  [
{
 "persName":
 "Arthur Schnitzler",
 "ref":
 ""}],
 "listPlace":
  [
 {
 "placeName":
 "Raimund-Theater",
 "ref":
 ""}
 ]
}
}] 