[{
 "type":
 "schnitzler-tagebuch",
 "color":
 "#037a33",
 "filename":
 "entry__1903-05-22",
 "caption":
 "Tagebuch",
 "idno":
 "https://schnitzler-tagebuch.acdh.oeaw.ac.at/entry__1903-05-22.html",
 "head":
 "Tagebuch, 22. Mai 1903",
 "desc":
{"listPerson":
  [
{
 "persName":
 "Edmund Markbreiter",
 "ref":
 "person_17899"},
 {
 "persName":
 "Marie Reinhard",
 "ref":
 "person_19150"},
 {
 "persName":
 "Johann Schnitzler",
 "ref":
 "person_19824"}],
 "listBibl":
  [
 {
 "title":
 "Bruder Straubinger",
 "ref":
 "pmb78513"}
 ],
 "listPlace":
  [
 {
 "placeName":
 "Vereinigte Staaten von Amerika (USA)",
 "ref":
 "pmb43406"}
 ,  {
 "placeName":
 "Schopenhauergasse",
 "ref":
 "pmb92520"}
 ]
}
}, {
 "type":
 "schnitzler-briefe",
 "color":
 "#A63437",
 "filename":
 "L03373",
 "caption":
 "Briefe mit Autorinnen und Autoren",
 "idno":
 "https://schnitzler-briefe.acdh.oeaw.ac.at/L03373.html",
 "head":
 "Paul Goldmann an Arthur Schnitzler, 2[2?]. 5. [1903]",
 "desc":
{"listPerson":
  [
{
 "persName":
 "Paul Goldmann",
 "ref":
 "pmb11485"},
 {
 "persName":
 "Arthur Schnitzler",
 "ref":
 "pmb2121"},
 {
 "persName":
 "Paul Goldmann",
 "ref":
 "pmb11485"},
 {
 "persName":
 "Olga Schnitzler",
 "ref":
 "pmb2173"},
 {
 "persName":
 "Julius Elias",
 "ref":
 "pmb11246"},
 {
 "persName":
 "Otto Brahm",
 "ref":
 "pmb10986"},
 {
 "persName":
 "Georg Hirschfeld",
 "ref":
 "pmb11701"},
 {
 "persName":
 "Elly Petersen",
 "ref":
 "pmb9233"},
 {
 "persName":
 "Paul Jonas",
 "ref":
 "pmb4532"},
 {
 "persName":
 "Hugo von Hofmannsthal",
 "ref":
 "pmb11740"},
 {
 "persName":
 "Oscar Wilde",
 "ref":
 "pmb13115"},
 {
 "persName":
 "Felix Paul Greve",
 "ref":
 "pmb41972"},
 {
 "persName":
 "Johannes Gaulke",
 "ref":
 "pmb146954"},
 {
 "persName":
 "Theodore Rottenberg",
 "ref":
 "pmb23674"},
 {
 "persName":
 "Irene Triesch",
 "ref":
 "pmb12977"}],
 "listBibl":
  [
 {
 "title":
 "Fink und Fliederbusch. Komödie in drei Akten",
 "ref":
 "pmb30881"}
 ,  {
 "title":
 "Berliner Theater. (»Lebendige Stunden« von Arthur Schnitzler.)",
 "ref":
 "pmb144122"}
 ,  {
 "title":
 "Lebendige Stunden. Vier Einakter",
 "ref":
 "pmb29863"}
 ,  {
 "title":
 "Dorian Grays Bildnis",
 "ref":
 "pmb146947"}
 ,  {
 "title":
 "The picture of Dorian Gray",
 "ref":
 "pmb77598"}
 ,  {
 "title":
 "Dorian Gray",
 "ref":
 "pmb77594"}
 ,  {
 "title":
 "Der Schleier der Beatrice. Schauspiel in fünf Akten",
 "ref":
 "pmb29857"}
 ],
 "listPlace":
  [
 {
 "placeName":
 "Berlin",
 "ref":
 "pmb168"}
 ,  {
 "placeName":
 "Wien",
 "ref":
 "pmb50"}
 ,  {
 "placeName":
 "Dessauer Straße",
 "ref":
 "pmb40583"}
 ,  {
 "placeName":
 "Italien",
 "ref":
 "pmb40306"}
 ,  {
 "placeName":
 "Südtirol",
 "ref":
 "pmb969"}
 ,  {
 "placeName":
 "Minden",
 "ref":
 "pmb58843"}
 ,  {
 "placeName":
 "Leipzig",
 "ref":
 "pmb864"}
 ,  {
 "placeName":
 "Schauspielhaus Leipzig",
 "ref":
 "pmb146964"}
 ],
 "listOrg":
  [
 {
 "orgName":
 "J. C. C. Bruns",
 "ref":
 "pmb146925"}
 ,  {
 "orgName":
 "Verlag Max Spohr",
 "ref":
 "pmb146958"}
 ,  {
 "orgName":
 "Deutsches Theater Berlin",
 "ref":
 "pmb35597"}
 ]
}
}, {
 "type":
 "wienerschnitzler",
 "color":
 "#6F5106",
 "caption":
 "Wiener Schnitzler",
 "idno":
 "https://wienerschnitzler.org/tag.html#1903-05-22",
 "head":
 "Wien",
 "desc":
{"listPlace":
  [
 {
 "placeName":
 "VI., Mariahilf",
 "ref":
 ""}
 ,  {
 "placeName":
 "XVIII., Währing",
 "ref":
 ""}
 ,  {
 "placeName":
 "IX., Alsergrund",
 "ref":
 ""}
 ]
}
}, {
 "type":
 "schnitzler-kultur",
 "color":
 "#6B4C5A",
 "filename":
 "pmb209292",
 "caption":
 "Kulturveranstaltungen",
 "idno":
 "https://schnitzler-kultur.acdh.oeaw.ac.at/pmb209292.html",
 "head":
 "Aufführung von Bruder Straubinger, 22.5.1903",
 "desc":
{"listOrg":
  [
 {
 "orgName":
 "Theater an der Wien",
 "ref":
 ""}
 ],
 "listBibl":
  [
 {
 "title":
 "Bruder Straubinger",
 "ref":
 ""}
 ],
 "listPerson":
  [
{
 "persName":
 "Arthur Schnitzler",
 "ref":
 ""}],
 "listPlace":
  [
 {
 "placeName":
 "Theater an der Wien",
 "ref":
 ""}
 ]
}
}] 