[{
 "type":
 "schnitzler-tagebuch",
 "color":
 "#037a33",
 "filename":
 "entry__1903-08-21",
 "caption":
 "Tagebuch",
 "idno":
 "https://schnitzler-tagebuch.acdh.oeaw.ac.at/entry__1903-08-21.html",
 "head":
 "Tagebuch, 21. August 1903",
 "desc":
{"listPlace":
  [
 {
 "placeName":
 "Lavarone",
 "ref":
 "pmb461"}
 ,  {
 "placeName":
 "Caldonazzo",
 "ref":
 "pmb90428"}
 ,  {
 "placeName":
 "Trient",
 "ref":
 "pmb954"}
 ]
}
}, {
 "type":
 "wienerschnitzler",
 "color":
 "#ECDA98",
 "caption":
 "Wiener Schnitzler",
 "idno":
 "https://wienerschnitzler.org/tag.html#1903-08-21",
 "head":
 "Caldonazzo"
}, {
 "type":
 "wienerschnitzler",
 "color":
 "#ECDA98",
 "caption":
 "Wiener Schnitzler",
 "idno":
 "https://wienerschnitzler.org/tag.html#1903-08-21",
 "head":
 "Lavarone",
 "desc":
{"listPlace":
  [
 {
 "placeName":
 "Grand Hotel Lavarone",
 "ref":
 ""}
 ]
}
}, {
 "type":
 "wienerschnitzler",
 "color":
 "#ECDA98",
 "caption":
 "Wiener Schnitzler",
 "idno":
 "https://wienerschnitzler.org/tag.html#1903-08-21",
 "head":
 "Trient"
}, {
 "type":
 "kalliope-verbund",
 "color":
 "#003574",
 "caption":
 "Kalliope Verbundkatalog",
 "idno":
 "http://kalliope-verbund.info/DE-2498-HS00035732",
 "head":
 "Guggenheim, Clementine an Schnitzler, Arthur [Briefe]",
 "text":
 "1 Bl."
}] 