[{
 "type":
 "schnitzler-tagebuch",
 "color":
 "#037a33",
 "filename":
 "entry__1903-12-02",
 "caption":
 "Tagebuch",
 "idno":
 "https://schnitzler-tagebuch.acdh.oeaw.ac.at/entry__1903-12-02.html",
 "head":
 "Tagebuch, 2. Dezember 1903",
 "desc":
{"listPerson":
  [
{
 "persName":
 "Gustav Frid",
 "ref":
 "person_15194"},
 {
 "persName":
 "Max von Rosenberg",
 "ref":
 "person_19374"}],
 "listPlace":
  [
 {
 "placeName":
 "Brüssel",
 "ref":
 "pmb862"}
 ,  {
 "placeName":
 "Bohemia",
 "ref":
 "pmb90376"}
 ]
}
}, {
 "type":
 "schnitzler-orte",
 "color":
 "#045344",
 "filename":
 "entity/50/",
 "caption":
 "Aufenthaltsorte",
 "idno":
 "https://pmb.acdh.oeaw.ac.at/entity/50/",
 "head":
 "Wien"
}, {
 "type":
 "schnitzler-orte",
 "color":
 "#045344",
 "filename":
 "entity/192320/",
 "caption":
 "Aufenthaltsorte",
 "idno":
 "https://pmb.acdh.oeaw.ac.at/entity/192320/",
 "head":
 "Zirkusgasse 2"
}, {
 "type":
 "schnitzler-events",
 "color":
 "#9BC53D",
 "filename":
 "entity/209304/",
 "caption":
 "Ereignisse in der PMB",
 "idno":
 "https://pmb.acdh.oeaw.ac.at/entity/209304/",
 "head":
 "Auftritt von Böhmisches Quartett, 2.12.1903",
 "desc":
{"listOrg":
  [
 {
 "orgName":
 "Böhmisches Quartett",
 "ref":
 ""}
 ],
 "listPerson":
  [
{
 "persName":
 "Arthur Schnitzler",
 "ref":
 ""}]
}
}] 