[{
 "type":
 "schnitzler-orte",
 "idno":
 "https://pmb.acdh.oeaw.ac.at/entity/50/",
 "head":
 "Wien"
}, {
 "type":
 "schnitzler-tagebuch",
 "idno":
 "https://schnitzler-tagebuch.acdh.oeaw.ac.at/entry__1903-04-01.html",
 "head":
 "Tagebuch, 1. April 1903",
 "desc":
{"listPerson":
  [
{
 "persName":
 "Paul Staal",
 "ref":
 "person_20312"}],
 "listPlace":
  [
 {
 "placeName":
 "Trutnov",
 "ref":
 "pmb91930"}
 ]}

}, {
 "type":
 "schnitzler-bahr",
 "idno":
 "https://schnitzler-bahr.acdh.oeaw.ac.at/L041643.html",
 "head":
 "Schnitzler: Widmungsexemplar Reigen, April 1903",
 "desc":
{"listPerson":
  [
{
 "persName":
 "Hermann Bahr",
 "ref":
 "pmb10815"}],
 "listBibl":
  [
 {
 "title":
 "Reigen. Zehn Dialoge",
 "ref":
 "pmb29855"}
 ],
 "listPlace":
  [
 {
 "placeName":
 "Wien",
 "ref":
 "pmb50"}
 ],
 "listOrg":
  [
 {
 "orgName":
 "Wiener Verlag",
 "ref":
 "pmb29636"}
 ]}

}] 