[{
 "type":
 "schnitzler-tagebuch",
 "color":
 "#037a33",
 "filename":
 "entry__1908-02-16",
 "caption":
 "Tagebuch",
 "idno":
 "https://schnitzler-tagebuch.acdh.oeaw.ac.at/entry__1908-02-16.html",
 "head":
 "Tagebuch, 16. Februar 1908",
 "desc":
{"listBibl":
  [
 {
 "title":
 "Der Ruf des Lebens. Schauspiel in drei Akten",
 "ref":
 "pmb29905"}
 ]
}
}, {
 "type":
 "wienerschnitzler",
 "color":
 "#6F5106",
 "caption":
 "Wiener Schnitzler",
 "idno":
 "https://wienerschnitzler.org/tag.html#1908-02-16",
 "head":
 "Semmering",
 "desc":
{"listPlace":
  [
 {
 "placeName":
 "Südbahnhotel [Semmering]",
 "ref":
 ""}
 ]
}
}, {
 "type":
 "schnitzler-cmif",
 "subtype":
 "#ya489e21-54d5-40de-a56d-f4548e894428",
 "color":
 "#654321",
 "caption":
 "Gedruckte Briefwechsel",
 "head":
 "Arthur Schnitzler an Otto Brahm, 16.2.1908",
 "source":
 "Der Briefwechsel Arthur Schnitzler – Otto Brahm. Vollständige Ausgabe. Hg., eingel. und erl. von Oskar Seidlin. Tübingen: Niemeyer, 1975."
}] 