[{
 "type":
 "schnitzler-tagebuch",
 "color":
 "#037a33",
 "filename":
 "entry__1910-02-02",
 "caption":
 "Tagebuch",
 "idno":
 "https://schnitzler-tagebuch.acdh.oeaw.ac.at/entry__1910-02-02.html",
 "head":
 "Tagebuch, 2. Februar 1910",
 "desc":
{"listPerson":
  [
{
 "persName":
 "Therese Behr",
 "ref":
 "person_13559"},
 {
 "persName":
 "Felix Salten",
 "ref":
 "person_19542"},
 {
 "persName":
 "Helene Schnitzler",
 "ref":
 "person_19823"},
 {
 "persName":
 "Julius Schnitzler",
 "ref":
 "person_19827"},
 {
 "persName":
 "Siegfried Trebitsch",
 "ref":
 "person_20796"},
 {
 "persName":
 "Clara Samuely",
 "ref":
 "person_19558"}],
 "listBibl":
  [
 {
 "title":
 "Das weite Land. Tragikomödie in fünf Akten",
 "ref":
 "pmb30207"}
 ],
 "listPlace":
  [
 {
 "placeName":
 "Heiligenstadt",
 "ref":
 "pmb90847"}
 ,  {
 "placeName":
 "Meissl &amp; Schadn",
 "ref":
 "pmb96"}
 ]
}
}, {
 "type":
 "wienerschnitzler",
 "color":
 "#6F5106",
 "caption":
 "Wiener Schnitzler",
 "idno":
 "https://wienerschnitzler.org/tag.html#1910-02-02",
 "head":
 "Wien",
 "desc":
{"listPlace":
  [
 {
 "placeName":
 "I., Innere Stadt",
 "ref":
 ""}
 ,  {
 "placeName":
 "XIX., Döbling",
 "ref":
 ""}
 ,  {
 "placeName":
 "XVIII., Währing",
 "ref":
 ""}
 ]
}
}, {
 "type":
 "URL",
 "subtype":
 "pmb",
 "filename":
 "entity/249748/",
 "idno":
 "https://pmb.acdh.oeaw.ac.at/entity/249748/",
 "head":
 "Liederabend von Therese Schnabel-Behr, 2.2.1910",
 "desc":
{"listPerson":
  [
{
 "persName":
 "Arthur Schnitzler",
 "ref":
 ""},
 {
 "persName":
 "Therese Behr-Schnabel",
 "ref":
 ""},
 {
 "persName":
 "Artur Schnabel",
 "ref":
 ""}],
 "listPlace":
  [
 {
 "placeName":
 "Bösendorfer-Saal",
 "ref":
 ""}
 ]
}
}, {
 "type":
 "schnitzler-cmif",
 "subtype":
 "#s364f351-b14a-4d77-b480-295e58878c66",
 "color":
 "#654321",
 "caption":
 "Gedruckte Briefwechsel",
 "head":
 "Alfred von Berger an Arthur Schnitzler, 2.2.1910",
 "source":
 "Hans Peter Buohler: Arthur Schnitzlers »Medardus Affairen« Teil 1: Korrespondenzen. In: Hofmannsthal-Jahrbuch ⋅ Zur europäischen Moderne, Jg. 19 (2011), S. 79–215."
}] 