[{
 "type":
 "schnitzler-tagebuch",
 "color":
 "#037a33",
 "filename":
 "entry__1910-11-27",
 "caption":
 "Tagebuch",
 "idno":
 "https://schnitzler-tagebuch.acdh.oeaw.ac.at/entry__1910-11-27.html",
 "head":
 "Tagebuch, 27. November 1910",
 "desc":
{"listPerson":
  [
{
 "persName":
 "Gisela Hajek",
 "ref":
 "person_15854"},
 {
 "persName":
 "Markus Hajek",
 "ref":
 "person_15855"},
 {
 "persName":
 "Marie Hofteufel",
 "ref":
 "person_16299"},
 {
 "persName":
 "Kranz",
 "ref":
 "person_17091"},
 {
 "persName":
 "Helene Schnitzler",
 "ref":
 "person_19823"},
 {
 "persName":
 "Julius Schnitzler",
 "ref":
 "person_19827"},
 {
 "persName":
 "Anna Sikora",
 "ref":
 "person_20523"},
 {
 "persName":
 "Albert Heine",
 "ref":
 "person_16046"},
 {
 "persName":
 "Konrad Loewe",
 "ref":
 "person_17642"},
 {
 "persName":
 "Arthur Kaufmann",
 "ref":
 "person_16770"}],
 "listBibl":
  [
 {
 "title":
 "Der junge Medardus. Dramatische Historie in einem Vorspiel und fünf Aufzügen",
 "ref":
 "pmb29937"}
 ,  {
 "title":
 "Der Ruf des Lebens. Schauspiel in drei Akten",
 "ref":
 "pmb29905"}
 ],
 "listPlace":
  [
 {
 "placeName":
 "Michaelerberg",
 "ref":
 "pmb91239"}
 ]
}
}, {
 "type":
 "schnitzler-briefe",
 "color":
 "#A63437",
 "filename":
 "L03628",
 "caption":
 "Briefe mit Autorinnen und Autoren",
 "idno":
 "https://schnitzler-briefe.acdh.oeaw.ac.at/L03628.html",
 "head":
 "Stefan Zweig an Arthur Schnitzler, 27. 11. 1910",
 "desc":
{"listPerson":
  [
{
 "persName":
 "Stefan Zweig",
 "ref":
 "pmb13212"}],
 "listBibl":
  [
 {
 "title":
 "Der Schleier der Beatrice. Schauspiel in fünf Akten",
 "ref":
 "pmb29857"}
 ,  {
 "title":
 "Der junge Medardus. Dramatische Historie in einem Vorspiel und fünf Aufzügen",
 "ref":
 "pmb29937"}
 ],
 "listPlace":
  [
 {
 "placeName":
 "Burgtheater",
 "ref":
 "pmb14"}
 ,  {
 "placeName":
 "Kochgasse 8",
 "ref":
 "pmb249577"}
 ,  {
 "placeName":
 "Wien",
 "ref":
 "pmb50"}
 ]
}
}, {
 "type":
 "wienerschnitzler",
 "color":
 "#ECDA98",
 "caption":
 "Wiener Schnitzler",
 "idno":
 "https://wienerschnitzler.org/tag.html#1910-11-27",
 "head":
 "Wien",
 "desc":
{"listPlace":
  [
 {
 "placeName":
 "XVIII., Währing",
 "ref":
 ""}
 ,  {
 "placeName":
 "I., Innere Stadt",
 "ref":
 ""}
 ]
}
}, {
 "type":
 "schnitzler-events",
 "color":
 "#9BC53D",
 "filename":
 "entity/251446/",
 "caption":
 "Ereignisse in der PMB",
 "idno":
 "https://pmb.acdh.oeaw.ac.at/entity/251446/",
 "head":
 "Aufführung von Der junge Medardus, 27.11.1910",
 "desc":
{"listOrg":
  [
 {
 "orgName":
 "Burgtheater",
 "ref":
 ""}
 ],
 "listBibl":
  [
 {
 "title":
 "Der junge Medardus. Dramatische Historie in einem Vorspiel und fünf Aufzügen",
 "ref":
 ""}
 ],
 "listPerson":
  [
{
 "persName":
 "Arthur Schnitzler",
 "ref":
 ""}],
 "listPlace":
  [
 {
 "placeName":
 "Burgtheater",
 "ref":
 ""}
 ]
}
}, {
 "type":
 "kalliope-verbund",
 "color":
 "#003574",
 "caption":
 "Kalliope Verbundkatalog",
 "idno":
 "http://kalliope-verbund.info/DE-2498-HS00034330",
 "head":
 "Fuchs, ... an Schnitzler, Arthur [Briefe]",
 "text":
 "2 Bl."
}] 