[{
 "type":
 "schnitzler-tagebuch",
 "color":
 "#037a33",
 "filename":
 "entry__1913-01-18",
 "caption":
 "Tagebuch",
 "idno":
 "https://schnitzler-tagebuch.acdh.oeaw.ac.at/entry__1913-01-18.html",
 "head":
 "Tagebuch, 18. Januar 1913",
 "desc":
{"listPerson":
  [
{
 "persName":
 "Leopold von Andrian-Werburg",
 "ref":
 "person_13202"},
 {
 "persName":
 "Eugenie Bachrach",
 "ref":
 "person_13355"},
 {
 "persName":
 "Stefanie Bachrach",
 "ref":
 "person_13359"},
 {
 "persName":
 "Lula Gmeiner",
 "ref":
 "person_15486"},
 {
 "persName":
 "Josef Halban",
 "ref":
 "person_15857"},
 {
 "persName":
 "Carl Krug",
 "ref":
 "person_17152"},
 {
 "persName":
 "Robert Michel",
 "ref":
 "person_18147"},
 {
 "persName":
 "Alberto Stringa",
 "ref":
 "person_20532"},
 {
 "persName":
 "Marianne Giustiniani",
 "ref":
 "person_21600"}],
 "listBibl":
  [
 {
 "title":
 "Professor Bernhardi. Komödie in fünf Akten",
 "ref":
 "pmb30203"}
 ,  {
 "title":
 "Im Spiel der Sommerlüfte. In drei Aufzügen",
 "ref":
 "pmb30945"}
 ],
 "listPlace":
  [
 {
 "placeName":
 "Liberec",
 "ref":
 "pmb47966"}
 ]
}
}, {
 "type":
 "wienerschnitzler",
 "color":
 "#6F5106",
 "caption":
 "Wiener Schnitzler",
 "idno":
 "https://wienerschnitzler.org/tag.html#1913-01-18",
 "head":
 "Wien",
 "desc":
{"listPlace":
  [
 {
 "placeName":
 "IX., Alsergrund",
 "ref":
 ""}
 ,  {
 "placeName":
 "XVIII., Währing",
 "ref":
 ""}
 ,  {
 "placeName":
 "I., Innere Stadt",
 "ref":
 ""}
 ]
}
}, {
 "type":
 "URL",
 "subtype":
 "schnitzler-kultur",
 "filename":
 "pmb209666",
 "idno":
 "https://schnitzler-kultur.acdh.oeaw.ac.at/pmb209666.html",
 "head":
 "Gesangskonzert von Lula Gmeiner, 18.1.1913",
 "desc":
{"listOrg":
  [
 {
 "orgName":
 "Gesellschaft der Musikfreunde",
 "ref":
 ""}
 ],
 "listPerson":
  [
{
 "persName":
 "Lula Gmeiner",
 "ref":
 ""},
 {
 "persName":
 "Arthur Schnitzler",
 "ref":
 ""}],
 "listPlace":
  [
 {
 "placeName":
 "Bösendorfer-Saal",
 "ref":
 ""}
 ]
}
}] 