[{
 "type":
 "schnitzler-tagebuch",
 "color":
 "#037a33",
 "filename":
 "entry__1913-03-03",
 "caption":
 "Tagebuch",
 "idno":
 "https://schnitzler-tagebuch.acdh.oeaw.ac.at/entry__1913-03-03.html",
 "head":
 "Tagebuch, 3. März 1913",
 "desc":
{"listPerson":
  [
{
 "persName":
 "Eugenie Bachrach",
 "ref":
 "person_13355"},
 {
 "persName":
 "Albert Bassermann",
 "ref":
 "person_13457"},
 {
 "persName":
 "Emil Geyer",
 "ref":
 "person_15412"},
 {
 "persName":
 "Julius Schnitzler",
 "ref":
 "person_19827"}],
 "listBibl":
  [
 {
 "title":
 "Große Szene",
 "ref":
 "pmb31429"}
 ,  {
 "title":
 "Zwischenspiel. Komödie in drei Akten",
 "ref":
 "pmb29903"}
 ]
}
}, {
 "type":
 "schnitzler-orte",
 "color":
 "#045344",
 "filename":
 "entity/50/",
 "caption":
 "Aufenthaltsorte",
 "idno":
 "https://pmb.acdh.oeaw.ac.at/entity/50/",
 "head":
 "Wien"
}, {
 "type":
 "schnitzler-cmif",
 "subtype":
 "#asbw_0a380dfe-61d4-4b9e-8641-01eba8e50760",
 "color":
 "#654321",
 "caption":
 "Gedruckte Briefwechsel",
 "head":
 "Erhalt von Richard Beer-Hofmann, Paula Beer-Hofmann an Arthur Schnitzler, 28. 2. 1913",
 "source":
 "Arthur Schnitzler – Briefwechsel mit Autorinnen und Autoren. Digitale Edition herausgegeben von Martin Anton Müller, Gerd-Hermann Susen und Laura Untner, 2018–[2024]"
}] 