{
 "date":
 {
 "when-iso":
 "1915-10-17",
 "written":
 "Sonntag, 17. Oktober 1915"
},
"listEvent":
 [{
 "type":
 "schnitzler-orte",
 "idno":
 "https://pmb.acdh.oeaw.ac.at/entity/50/",
 "head":
 "Wien"
}, {
 "type":
 "schnitzler-cmif",
 "subtype":
 "#dc95034c-3e70-47e1-9072-3fc75d84b47a",
 "head":
 "Fritz Unruh an Arthur Schnitzler, 17.10.1915",
 "desc":
{"listPerson":
  [
{
 "persName":
 "Unruh, Fritz",
 "ref":
 "https://d-nb.info/gnd/118625527"}],
 "bibl":
 "Ulrich K. Goldsmith: Der Briefwechsel Fritz von Unruhs mit Arthur Schnitzler. In: Modern Austrian Literature, Jg. 10, 1977, H. 3/4, S. 69-128."}

}, {
 "type":
 "schnitzler-tagebuch",
 "idno":
 "https://schnitzler-tagebuch.acdh.oeaw.ac.at/entry__1915-10-17.html",
 "head":
 "Tagebuch, 17. Oktober 1915",
 "desc":
{"listPerson":
  [
{
 "persName":
 "Eugenie Bachrach",
 "ref":
 "person_13355"},
 {
 "persName":
 "Stefanie Bachrach",
 "ref":
 "person_13359"},
 {
 "persName":
 "Max Eugen Burckhard",
 "ref":
 "person_14065"},
 {
 "persName":
 "Max Devrient",
 "ref":
 "person_14434"},
 {
 "persName":
 "Alfred Gerasch",
 "ref":
 "person_15396"},
 {
 "persName":
 "Mathilde Kutschera",
 "ref":
 "person_17222"},
 {
 "persName":
 "Victor Kutschera",
 "ref":
 "person_17223"},
 {
 "persName":
 "Louise Schnitzler",
 "ref":
 "person_19831"},
 {
 "persName":
 "Alberto Stringa",
 "ref":
 "person_20532"},
 {
 "persName":
 "Rudolf Urbantschitsch",
 "ref":
 "person_20892"},
 {
 "persName":
 "Else Wohlgemuth",
 "ref":
 "person_21423"},
 {
 "persName":
 "Berta Zuckerkandl",
 "ref":
 "person_21594"},
 {
 "persName":
 "Marianne Giustiniani",
 "ref":
 "person_21600"}],
 "listBibl":
  [
 {
 "title":
 "Die Hirtenflöte. Novelle",
 "ref":
 "pmb30213"}
 ,  {
 "title":
 "Komödie der Worte. Drei Einakter",
 "ref":
 "pmb30717"}
 ,  {
 "title":
 "Große Szene",
 "ref":
 "pmb31429"}
 ,  {
 "title":
 "Liebelei. Schauspiel in drei Akten",
 "ref":
 "pmb29917"}
 ],
 "listPlace":
  [
 {
 "placeName":
 "Monte Baldo",
 "ref":
 "pmb91280"}
 ]}

}] 
}