[{
 "type":
 "schnitzler-tagebuch",
 "color":
 "#037a33",
 "filename":
 "entry__1918-08-29",
 "caption":
 "Tagebuch",
 "idno":
 "https://schnitzler-tagebuch.acdh.oeaw.ac.at/entry__1918-08-29.html",
 "head":
 "Tagebuch, 29. August 1918",
 "desc":
{"listPerson":
  [
{
 "persName":
 "Freudenthal",
 "ref":
 "person_15176"},
 {
 "persName":
 "Reinhard Koester",
 "ref":
 "person_16983"},
 {
 "persName":
 "Elisabeth Steinrück",
 "ref":
 "person_20386"}],
 "listBibl":
  [
 {
 "title":
 "Peregrinus",
 "ref":
 "pmb80805"}
 ]
}
}, {
 "type":
 "schnitzler-orte",
 "color":
 "#045344",
 "filename":
 "entity/667/",
 "caption":
 "Aufenthaltsorte",
 "idno":
 "https://pmb.acdh.oeaw.ac.at/entity/667/",
 "head":
 "Garmisch-Partenkirchen"
}, {
 "type":
 "schnitzler-cmif",
 "subtype":
 "#asbw_0a380dfe-61d4-4b9e-8641-01eba8e50760",
 "color":
 "#654321",
 "caption":
 "Gedruckte Briefwechsel",
 "head":
 "Erhalt von Hermann Bahr an Arthur Schnitzler, 25. 8. 1918",
 "source":
 "Arthur Schnitzler – Briefwechsel mit Autorinnen und Autoren. Digitale Edition herausgegeben von Martin Anton Müller, Gerd-Hermann Susen und Laura Untner, 2018–[2024]"
}, {
 "type":
 "schnitzler-cmif",
 "subtype":
 "#asbw_0a380dfe-61d4-4b9e-8641-01eba8e50760",
 "color":
 "#654321",
 "caption":
 "Gedruckte Briefwechsel",
 "head":
 "Erhalt von Richard Beer-Hofmann an Arthur Schnitzler, 28. 8. 1918",
 "source":
 "Arthur Schnitzler – Briefwechsel mit Autorinnen und Autoren. Digitale Edition herausgegeben von Martin Anton Müller, Gerd-Hermann Susen und Laura Untner, 2018–[2024]"
}] 