[{
 "type":
 "schnitzler-tagebuch",
 "color":
 "#037a33",
 "filename":
 "entry__1920-09-14",
 "caption":
 "Tagebuch",
 "idno":
 "https://schnitzler-tagebuch.acdh.oeaw.ac.at/entry__1920-09-14.html",
 "head":
 "Tagebuch, 14. September 1920",
 "desc":
{"listPerson":
  [
{
 "persName":
 "Lili Schnitzler",
 "ref":
 "person_14130"},
 {
 "persName":
 "Anna Reiter",
 "ref":
 "person_19170"},
 {
 "persName":
 "Franzl",
 "ref":
 "person_15152"},
 {
 "persName":
 "Olga Schnitzler",
 "ref":
 "person_19832"}],
 "listPlace":
  [
 {
 "placeName":
 "Altaussee",
 "ref":
 "pmb90229"}
 ,  {
 "placeName":
 "Pötschenhöhe",
 "ref":
 "pmb91518"}
 ,  {
 "placeName":
 "Gosaumühle",
 "ref":
 "pmb90743"}
 ,  {
 "placeName":
 "Gosau",
 "ref":
 "pmb51797"}
 ]
}
}, {
 "type":
 "URL",
 "subtype":
 "wienerschnitzler",
 "head":
 "Altaussee",
 "desc":
{"listPlace":
  [
 {
 "placeName":
 "Hotel am See",
 "ref":
 ""}
 ]
}
}, {
 "type":
 "URL",
 "subtype":
 "wienerschnitzler",
 "head":
 "Gosau",
 "desc":
{"listPlace":
  [
 {
 "placeName":
 "Hotel und Restaurant Brandwirt",
 "ref":
 ""}
 ]
}
}, {
 "type":
 "URL",
 "subtype":
 "wienerschnitzler",
 "head":
 "Gosaumühle"
}, {
 "type":
 "URL",
 "subtype":
 "wienerschnitzler",
 "head":
 "Pötschenhöhe"
}, {
 "type":
 "URL",
 "subtype":
 "wienerschnitzler",
 "head":
 "Steeg",
 "desc":
{"listPlace":
  [
 {
 "placeName":
 "Hotel Klachl",
 "ref":
 ""}
 ]
}
}, {
 "type":
 "URL",
 "subtype":
 "wienerschnitzler",
 "head":
 "Hallstätter See"
}] 