[{
 "type":
 "schnitzler-orte",
 "idno":
 "https://pmb.acdh.oeaw.ac.at/entity/50/",
 "head":
 "Wien"
}, {
 "type":
 "schnitzler-tagebuch",
 "idno":
 "https://schnitzler-tagebuch.acdh.oeaw.ac.at/entry__1923-10-17.html",
 "head":
 "Tagebuch, 17. Oktober 1923",
 "desc":
{"listPerson":
  [
{
 "persName":
 "Catherine Barjanski",
 "ref":
 "person_13424"},
 {
 "persName":
 "Richard Beer-Hofmann",
 "ref":
 "person_13551"},
 {
 "persName":
 "Hans Jacob",
 "ref":
 "person_16462"},
 {
 "persName":
 "Josef Peter",
 "ref":
 "person_18722"},
 {
 "persName":
 "Norbert Hoffmann",
 "ref":
 "person_16277"}]}

}] 