[{
 "type":
 "schnitzler-orte",
 "idno":
 "https://pmb.acdh.oeaw.ac.at/entity/50/",
 "head":
 "Wien"
}, {
 "type":
 "Arthur-Schnitzler-digital",
 "idno":
 "https://www.schnitzler-edition.net",
 "head":
 "Spiel im Morgengrauen, Typoskript",
 "desc":
{}

}, {
 "type":
 "schnitzler-tagebuch",
 "idno":
 "https://schnitzler-tagebuch.acdh.oeaw.ac.at/entry__1923-10-13.html",
 "head":
 "Tagebuch, 13. Oktober 1923",
 "desc":
{"listPerson":
  [
{
 "persName":
 "Hedy Kempny",
 "ref":
 "person_16807"},
 {
 "persName":
 "Heinrich Schnitzler",
 "ref":
 "person_19822"}],
 "listBibl":
  [
 {
 "title":
 "Spiel im Morgengrauen. Novelle",
 "ref":
 "pmb32131"}
 ],
 "listPlace":
  [
 {
 "placeName":
 "Pötzleinsdorf",
 "ref":
 "pmb169"}
 ]}

}] 