[{
 "type":
 "schnitzler-tagebuch",
 "color":
 "#037a33",
 "filename":
 "entry__1925-06-13",
 "caption":
 "Tagebuch",
 "idno":
 "https://schnitzler-tagebuch.acdh.oeaw.ac.at/entry__1925-06-13.html",
 "head":
 "Tagebuch, 13. Juni 1925",
 "desc":
{"listPerson":
  [
{
 "persName":
 "Ludwig van Beethoven",
 "ref":
 "person_13555"},
 {
 "persName":
 "Lili Schnitzler",
 "ref":
 "person_14130"},
 {
 "persName":
 "Antonín Dvořák",
 "ref":
 "person_14579"},
 {
 "persName":
 "Arnold Rosé",
 "ref":
 "person_19351"},
 {
 "persName":
 "Julius Schnitzler",
 "ref":
 "person_19827"},
 {
 "persName":
 "Bedřich Smetana",
 "ref":
 "person_20172"},
 {
 "persName":
 "Franz Peter Schubert",
 "ref":
 "person_19902"}],
 "listBibl":
  [
 {
 "title":
 "Therese. Chronik eines Frauenlebens",
 "ref":
 "pmb30817"}
 ]
}
}, {
 "type":
 "wienerschnitzler",
 "color":
 "#6F5106",
 "caption":
 "Wiener Schnitzler",
 "idno":
 "https://wienerschnitzler.org/tag.html#1925-06-13",
 "head":
 "Wien",
 "desc":
{"listPlace":
  [
 {
 "placeName":
 "VIII., Josefstadt",
 "ref":
 ""}
 ,  {
 "placeName":
 "XVIII., Währing",
 "ref":
 ""}
 ]
}
}, {
 "type":
 "kalliope-verbund",
 "color":
 "#003574",
 "caption":
 "Kalliope Verbundkatalog",
 "idno":
 "http://kalliope-verbund.info/DE-2498-HS00048444",
 "head":
 "Schnitzler, Arthur an F. A. C. Prestel [Briefe]",
 "text":
 "1 Bl.Durchschl.",
 "desc":
{"listPerson":
  [
{
 "persName":
 "F. A. C. Prestel",
 "ref":
 "http://d-nb.info/gnd/252499-5"}]
}
}] 