[{
 "type":
 "schnitzler-tagebuch",
 "color":
 "#037a33",
 "filename":
 "entry__1925-10-19",
 "caption":
 "Tagebuch",
 "idno":
 "https://schnitzler-tagebuch.acdh.oeaw.ac.at/entry__1925-10-19.html",
 "head":
 "Tagebuch, 19. Oktober 1925",
 "desc":
{"listPerson":
  [
{
 "persName":
 "Richard Duschinsky",
 "ref":
 "person_14571"},
 {
 "persName":
 "Georg Engel",
 "ref":
 "person_14754"},
 {
 "persName":
 "Hedy Kempny",
 "ref":
 "person_16807"},
 {
 "persName":
 "Vilma Lichtenstern",
 "ref":
 "person_17510"},
 {
 "persName":
 "Lucie Mannheim",
 "ref":
 "person_17841"},
 {
 "persName":
 "Karl Michaelis",
 "ref":
 "person_18140"},
 {
 "persName":
 "Albert Patry",
 "ref":
 "person_18674"},
 {
 "persName":
 "Clara Katharina Pollaczek",
 "ref":
 "person_18863"},
 {
 "persName":
 "Heinrich Schnitzler",
 "ref":
 "person_19822"},
 {
 "persName":
 "Adolf von Sonnenthal",
 "ref":
 "person_20204"},
 {
 "persName":
 "Leopold Jessner",
 "ref":
 "person_16550"},
 {
 "persName":
 "Olga Schnitzler",
 "ref":
 "person_19832"},
 {
 "persName":
 "Hermann Sudermann",
 "ref":
 "person_20563"}],
 "listBibl":
  [
 {
 "title":
 "Fink und Fliederbusch. Komödie in drei Akten",
 "ref":
 "pmb30881"}
 ,  {
 "title":
 "Der Gang zum Weiher. Dramatische Dichtung",
 "ref":
 "pmb30775"}
 ,  {
 "title":
 "Der grüne Kakadu. Groteske in einem Akt",
 "ref":
 "pmb29843"}
 ,  {
 "title":
 "Das Märchen. Schauspiel in drei Aufzügen",
 "ref":
 "pmb29823"}
 ,  {
 "title":
 "Hannibal",
 "ref":
 "pmb78341"}
 ,  {
 "title":
 "Der Mann, den man ohrfeigt",
 "ref":
 "pmb81316"}
 ],
 "listPlace":
  [
 {
 "placeName":
 "Berlin",
 "ref":
 "pmb168"}
 ]
}
}, {
 "type":
 "wienerschnitzler",
 "color":
 "#6F5106",
 "caption":
 "Wiener Schnitzler",
 "idno":
 "https://wienerschnitzler.org/tag.html#1925-10-19",
 "head":
 "Berlin",
 "desc":
{"listPlace":
  [
 {
 "placeName":
 "Hotel Esplanade [Berlin]",
 "ref":
 ""}
 ,  {
 "placeName":
 "Schauspielhaus Berlin",
 "ref":
 ""}
 ,  {
 "placeName":
 "Welserstraße 19",
 "ref":
 ""}
 ,  {
 "placeName":
 "Hohenzollerndamm 90",
 "ref":
 ""}
 ,  {
 "placeName":
 "Zum Austernmeyer",
 "ref":
 ""}
 ,  {
 "placeName":
 "Ufa-Palast am Zoo",
 "ref":
 ""}
 ]
}
}, {
 "type":
 "schnitzler-kultur",
 "color":
 "#6B4C5A",
 "filename":
 "pmb210770",
 "caption":
 "Kulturveranstaltungen",
 "idno":
 "https://schnitzler-kultur.acdh.oeaw.ac.at/pmb210770.html",
 "head":
 "Filmvorführung von He Who Gets Slapped, 19.10.1925",
 "desc":
{"listBibl":
  [
 {
 "title":
 "He Who Gets Slapped",
 "ref":
 ""}
 ],
 "listPerson":
  [
{
 "persName":
 "Arthur Schnitzler",
 "ref":
 ""},
 {
 "persName":
 "Karl Michaelis",
 "ref":
 ""}],
 "listPlace":
  [
 {
 "placeName":
 "Ufa-Palast am Zoo",
 "ref":
 ""}
 ]
}
}, {
 "type":
 "pollaczek",
 "color":
 "#1e81b0",
 "filename":
 "ckp289",
 "caption":
 "Pollaczek: Schnitzler und ich",
 "idno":
 "https://pollaczek.acdh.oeaw.ac.at/ckp289.html",
 "head":
 "Clara Katharina Pollaczek an Arthur Schnitzler, 19. Oktober 1925"
}, {
 "type":
 "pollaczek",
 "color":
 "#1e81b0",
 "filename":
 "ckp290",
 "caption":
 "Pollaczek: Schnitzler und ich",
 "idno":
 "https://pollaczek.acdh.oeaw.ac.at/ckp290.html",
 "head":
 "Arthur Schnitzler an Clara Katharina Pollaczek, 19. Oktober 1925"
}, {
 "type":
 "schnitzler-kino-buch",
 "subtype":
 "#ISBN978-3205787464",
 "color":
 "#B43C9C",
 "caption":
 "Kino",
 "head":
 "Schnitzler geht ins Kino in Berlin, 19. Oktober 1925",
 "source":
 "»A. ist manchmal wie ein kleines Kind«. Clara Katharina Pollaczek und Arthur Schnitzler gehen ins Kino. Herausgegeben von Stephan Kurz und Michael Rohrwasser unter Mitarbeit von Daniel Schopper. Wien, Köln, Weimar: Böhlau Verlag 2012."
}] 