[{
 "type":
 "schnitzler-tagebuch",
 "color":
 "#037a33",
 "filename":
 "entry__1925-10-30",
 "caption":
 "Tagebuch",
 "idno":
 "https://schnitzler-tagebuch.acdh.oeaw.ac.at/entry__1925-10-30.html",
 "head":
 "Tagebuch, 30. Oktober 1925",
 "desc":
{"listPerson":
  [
{
 "persName":
 "Pedro Calderón de la Barca",
 "ref":
 "person_14115"},
 {
 "persName":
 "Lili Schnitzler",
 "ref":
 "person_14130"},
 {
 "persName":
 "Felix Hansel",
 "ref":
 "person_15905"},
 {
 "persName":
 "Carl Eduard Klopfer",
 "ref":
 "person_16919"},
 {
 "persName":
 "Clara Katharina Pollaczek",
 "ref":
 "person_18863"},
 {
 "persName":
 "Paula Schmidl",
 "ref":
 "person_19756"},
 {
 "persName":
 "Julie Wassermann",
 "ref":
 "person_21109"},
 {
 "persName":
 "Josef Wiesel",
 "ref":
 "person_21310"},
 {
 "persName":
 "Eugen Pollak",
 "ref":
 "person_18880"},
 {
 "persName":
 "Jakob Wassermann",
 "ref":
 "person_21107"},
 {
 "persName":
 "Hugo von Hofmannsthal",
 "ref":
 "person_16293"}],
 "listBibl":
  [
 {
 "title":
 "Der Geist im Wort und der Geist in der Tat",
 "ref":
 "pmb30051"}
 ,  {
 "title":
 "Therese. Chronik eines Frauenlebens",
 "ref":
 "pmb30817"}
 ,  {
 "title":
 "Der Turm",
 "ref":
 "pmb76478"}
 ,  {
 "title":
 "Wallenstein",
 "ref":
 "pmb77041"}
 ],
 "listPlace":
  [
 {
 "placeName":
 "Italian Riviera",
 "ref":
 "pmb90942"}
 ]
}
}, {
 "type":
 "schnitzler-briefe",
 "color":
 "#A63437",
 "filename":
 "L03539",
 "caption":
 "Briefe mit Autorinnen und Autoren",
 "idno":
 "https://schnitzler-briefe.acdh.oeaw.ac.at/L03539.html",
 "head":
 "Franziska Goldmann an Arthur Schnitzler, [Ende Oktober 1925?]",
 "desc":
{"listPerson":
  [
{
 "persName":
 "Franziska Goldmann",
 "ref":
 "pmb17167"},
 {
 "persName":
 "Arthur Schnitzler",
 "ref":
 "pmb2121"},
 {
 "persName":
 "Franziska Goldmann",
 "ref":
 "pmb17167"},
 {
 "persName":
 "Paul Goldmann",
 "ref":
 "pmb11485"}],
 "listBibl":
  [
 {
 "title":
 "Fräulein Else",
 "ref":
 "pmb29941"}
 ],
 "listPlace":
  [
 {
 "placeName":
 "Berlin",
 "ref":
 "pmb168"}
 ,  {
 "placeName":
 "Wien",
 "ref":
 "pmb50"}
 ]
}
}, {
 "type":
 "wienerschnitzler",
 "color":
 "#6F5106",
 "caption":
 "Wiener Schnitzler",
 "idno":
 "https://wienerschnitzler.org/tag.html#1925-10-30",
 "head":
 "Wien",
 "desc":
{"listPlace":
  [
 {
 "placeName":
 "XVIII., Währing",
 "ref":
 ""}
 ,  {
 "placeName":
 "I., Innere Stadt",
 "ref":
 ""}
 ]
}
}] 