[{
 "type":
 "schnitzler-tagebuch",
 "color":
 "#037a33",
 "filename":
 "entry__1926-10-08",
 "caption":
 "Tagebuch",
 "idno":
 "https://schnitzler-tagebuch.acdh.oeaw.ac.at/entry__1926-10-08.html",
 "head":
 "Tagebuch, 8. Oktober 1926",
 "desc":
{"listPerson":
  [
{
 "persName":
 "Lili Kraus",
 "ref":
 "person_17110"},
 {
 "persName":
 "Clara Katharina Pollaczek",
 "ref":
 "person_18863"},
 {
 "persName":
 "Julius Schnitzler",
 "ref":
 "person_19827"}],
 "listBibl":
  [
 {
 "title":
 "Spiel im Morgengrauen. Novelle",
 "ref":
 "pmb32131"}
 ]
}
}, {
 "type":
 "wienerschnitzler",
 "color":
 "#6F5106",
 "caption":
 "Wiener Schnitzler",
 "idno":
 "https://wienerschnitzler.org/tag.html#1926-10-08",
 "head":
 "Wien",
 "desc":
{"listPlace":
  [
 {
 "placeName":
 "VIII., Josefstadt",
 "ref":
 ""}
 ,  {
 "placeName":
 "I., Innere Stadt",
 "ref":
 ""}
 ,  {
 "placeName":
 "XVIII., Währing",
 "ref":
 ""}
 ]
}
}, {
 "type":
 "URL",
 "subtype":
 "schnitzler-kultur",
 "filename":
 "pmb251171",
 "idno":
 "https://schnitzler-kultur.acdh.oeaw.ac.at/pmb251171.html",
 "head":
 "Ausstellungsbesuch Das Stadtbild Wiens in der bildenden Kunst, 8.10.1926",
 "desc":
{"listPerson":
  [
{
 "persName":
 "Arthur Schnitzler",
 "ref":
 ""}],
 "listPlace":
  [
 {
 "placeName":
 "Secession",
 "ref":
 ""}
 ]
}
}] 