[{
 "type":
 "schnitzler-tagebuch",
 "color":
 "#037a33",
 "filename":
 "entry__1927-02-23",
 "caption":
 "Tagebuch",
 "idno":
 "https://schnitzler-tagebuch.acdh.oeaw.ac.at/entry__1927-02-23.html",
 "head":
 "Tagebuch, 23. Februar 1927",
 "desc":
{"listPerson":
  [
{
 "persName":
 "Lili Schnitzler",
 "ref":
 "person_14130"},
 {
 "persName":
 "Herbert Cysarz",
 "ref":
 "person_14327"},
 {
 "persName":
 "Gisela Hajek",
 "ref":
 "person_15854"},
 {
 "persName":
 "Alexander Lernet-Holenia",
 "ref":
 "person_17466"},
 {
 "persName":
 "Emil Lucka",
 "ref":
 "person_17719"},
 {
 "persName":
 "Clara Katharina Pollaczek",
 "ref":
 "person_18863"},
 {
 "persName":
 "Franz Horch",
 "ref":
 "person_16355"},
 {
 "persName":
 "Hugo von Hofmannsthal",
 "ref":
 "person_16293"},
 {
 "persName":
 "Olga Schnitzler",
 "ref":
 "person_19832"}],
 "listBibl":
  [
 {
 "title":
 "Anatol",
 "ref":
 "pmb29935"}
 ,  {
 "title":
 "Der Geist im Wort und der Geist in der Tat",
 "ref":
 "pmb30051"}
 ,  {
 "title":
 "Der Gang zum Weiher. Dramatische Dichtung",
 "ref":
 "pmb30775"}
 ,  {
 "title":
 "Metropolis",
 "ref":
 "pmb80833"}
 ,  {
 "title":
 "Österreichische Komödie",
 "ref":
 "pmb80877"}
 ]
}
}, {
 "type":
 "schnitzler-orte",
 "color":
 "#045344",
 "caption":
 "Aufenthaltsorte",
 "head":
 "Wien",
 "desc":
{"listPlace":
  [
 {
 "placeName":
 "IX., Alsergrund",
 "ref":
 ""}
 ,  {
 "placeName":
 "I., Innere Stadt",
 "ref":
 ""}
 ,  {
 "placeName":
 "XVIII., Währing",
 "ref":
 ""}
 ]
}
}, {
 "type":
 "schnitzler-events",
 "color":
 "#9BC53D",
 "filename":
 "entity/210881/",
 "caption":
 "Ereignisse in der PMB",
 "idno":
 "https://pmb.acdh.oeaw.ac.at/entity/210881/",
 "head":
 "Filmvorführung von Metropolis, 23.2.1927",
 "desc":
{"listBibl":
  [
 {
 "title":
 "Metropolis",
 "ref":
 ""}
 ],
 "listPerson":
  [
{
 "persName":
 "Arthur Schnitzler",
 "ref":
 ""},
 {
 "persName":
 "Clara Katharina Pollaczek",
 "ref":
 ""}],
 "listPlace":
  [
 {
 "placeName":
 "Wien",
 "ref":
 ""}
 ]
}
}, {
 "type":
 "schnitzler-kino-buch",
 "subtype":
 "#ISBN978-3205787464",
 "color":
 "#B43C9C",
 "caption":
 "Kino",
 "head":
 "Schnitzler geht ins Kino, 23. Februar 1927",
 "source":
 "»A. ist manchmal wie ein kleines Kind«. Clara Katharina Pollaczek und Arthur Schnitzler gehen ins Kino. Herausgegeben von Stephan Kurz und Michael Rohrwasser unter Mitarbeit von Daniel Schopper. Wien, Köln, Weimar: Böhlau Verlag 2012."
}] 