[{
 "type":
 "schnitzler-tagebuch",
 "color":
 "#037a33",
 "filename":
 "entry__1928-11-16",
 "caption":
 "Tagebuch",
 "idno":
 "https://schnitzler-tagebuch.acdh.oeaw.ac.at/entry__1928-11-16.html",
 "head":
 "Tagebuch, 16. November 1928",
 "desc":
{"listPerson":
  [
{
 "persName":
 "Stefan Großmann",
 "ref":
 "person_15691"},
 {
 "persName":
 "Clara Katharina Pollaczek",
 "ref":
 "person_18863"},
 {
 "persName":
 "Stendhal",
 "ref":
 "person_20397"}],
 "listBibl":
  [
 {
 "title":
 "Chefredakteur Roth führt Krieg",
 "ref":
 "pmb76868"}
 ],
 "listPlace":
  [
 {
 "placeName":
 "Hasenauerstraße",
 "ref":
 "pmb383"}
 ,  {
 "placeName":
 "Semmering",
 "ref":
 "pmb91735"}
 ]
}
}, {
 "type":
 "wienerschnitzler",
 "color":
 "#ECDA98",
 "caption":
 "Wiener Schnitzler",
 "idno":
 "https://wienerschnitzler.org/tag.html#1928-11-16",
 "head":
 "Wien",
 "desc":
{"listPlace":
  [
 {
 "placeName":
 "XVIII., Währing",
 "ref":
 ""}
 ]
}
}, {
 "type":
 "wienerschnitzler",
 "color":
 "#ECDA98",
 "caption":
 "Wiener Schnitzler",
 "idno":
 "https://wienerschnitzler.org/tag.html#1928-11-16",
 "head":
 "Semmering",
 "desc":
{"listPlace":
  [
 {
 "placeName":
 "Südbahnhotel [Semmering]",
 "ref":
 ""}
 ]
}
}, {
 "type":
 "kalliope-verbund",
 "color":
 "#003574",
 "caption":
 "Kalliope Verbundkatalog",
 "idno":
 "http://kalliope-verbund.info/DE-2498-HS00032438",
 "head":
 "Blinzler, Josef an Schnitzler, Arthur [Briefe]",
 "text":
 "2 Bl."
}] 