[{
 "type":
 "schnitzler-tagebuch",
 "color":
 "#037a33",
 "filename":
 "entry__1928-01-16",
 "caption":
 "Tagebuch",
 "idno":
 "https://schnitzler-tagebuch.acdh.oeaw.ac.at/entry__1928-01-16.html",
 "head":
 "Tagebuch, 16. Januar 1928",
 "desc":
{"listPerson":
  [
{
 "persName":
 "von Vincent",
 "ref":
 "person_20968"}],
 "listBibl":
  [
 {
 "title":
 "Abenteurernovelle",
 "ref":
 "pmb30299"}
 ,  {
 "title":
 "Zug der Schatten",
 "ref":
 "pmb32049"}
 ]
}
}, {
 "type":
 "schnitzler-briefe",
 "color":
 "#A63437",
 "filename":
 "L03741",
 "caption":
 "Briefe mit Autorinnen und Autoren",
 "idno":
 "https://schnitzler-briefe.acdh.oeaw.ac.at/L03741.html",
 "head":
 "Arthur Schnitzler an Stefan Zweig, 16. 1. 1928",
 "desc":
{"listPerson":
  [
{
 "persName":
 "Arthur Schnitzler",
 "ref":
 "pmb2121"},
 {
 "persName":
 "Stefan Zweig",
 "ref":
 "pmb13212"},
 {
 "persName":
 "Stefan Zweig",
 "ref":
 "pmb13212"},
 {
 "persName":
 "Maxim Gorkij",
 "ref":
 "pmb2323"},
 {
 "persName":
 "Richard Specht",
 "ref":
 "pmb2456"}],
 "listBibl":
  [
 {
 "title":
 "Buch der Sprüche und Bedenken",
 "ref":
 "pmb30053"}
 ,  {
 "title":
 "Grenzen der Kritik",
 "ref":
 "pmb35806"}
 ,  {
 "title":
 "Sobranie sočinenij",
 "ref":
 "pmb295206"}
 ,  {
 "title":
 "Stefan Zweig. Versuch eines Bildnisses",
 "ref":
 "pmb296316"}
 ,  {
 "title":
 "Therese. Chronik eines Frauenlebens",
 "ref":
 "pmb30817"}
 ,  {
 "title":
 "Sternstunden der Menschheit",
 "ref":
 "pmb294825"}
 ,  {
 "title":
 "Drei Dichter ihres Lebens. Casanova – Stendhal – Tolstoi",
 "ref":
 "pmb293680"}
 ,  {
 "title":
 "Quiproquo. Komödie in drei Akten",
 "ref":
 "pmb293997"}
 ],
 "listPlace":
  [
 {
 "placeName":
 "Wien",
 "ref":
 "pmb50"}
 ,  {
 "placeName":
 "Salzburg",
 "ref":
 "pmb30"}
 ,  {
 "placeName":
 "Sternwartestraße 71",
 "ref":
 "pmb168815"}
 ,  {
 "placeName":
 "Russland",
 "ref":
 "pmb34438"}
 ],
 "listOrg":
  [
 {
 "orgName":
 "Wremja",
 "ref":
 "pmb294981"}
 ]
}
}, {
 "type":
 "wienerschnitzler",
 "color":
 "#6F5106",
 "caption":
 "Wiener Schnitzler",
 "idno":
 "https://wienerschnitzler.org/tag.html#1928-01-16",
 "head":
 "Wien",
 "desc":
{"listPlace":
  [
 {
 "placeName":
 "XVIII., Währing",
 "ref":
 ""}
 ]
}
}, {
 "type":
 "schnitzler-mikrofilme-daten",
 "color":
 "#6e7b8b",
 "filename":
 "1589032_0172",
 "caption":
 "Mikroverfilmung des Nachlasses",
 "idno":
 "https://schnitzler-mikrofilme.acdh.oeaw.ac.at/1589032_0172.html",
 "head":
 "Mappe A224",
 "text":
 "Datumsangabe auf Blatt von Zug der Schatten"
}, {
 "type":
 "kalliope-verbund",
 "color":
 "#003574",
 "caption":
 "Kalliope Verbundkatalog",
 "idno":
 "http://kalliope-verbund.info/DE-2498-HS00084465",
 "head":
 "Schnitzler, Arthur: Zug der Schatten [Dramatisches] (Manuskripttitel)",
 "text":
 "Letztes Objekt aus der Mappe. ca 200 Bl.Abschr. mit hs. Korr."
}] 