[{
 "type":
 "schnitzler-tagebuch",
 "color":
 "#037a33",
 "filename":
 "entry__1929-12-18",
 "caption":
 "Tagebuch",
 "idno":
 "https://schnitzler-tagebuch.acdh.oeaw.ac.at/entry__1929-12-18.html",
 "head":
 "Tagebuch, 18. Dezember 1929",
 "desc":
{"listPerson":
  [
{
 "persName":
 "Herbert Cysarz",
 "ref":
 "person_14327"},
 {
 "persName":
 "Julius Goldschl채ger",
 "ref":
 "person_15537"},
 {
 "persName":
 "Clara Katharina Pollaczek",
 "ref":
 "person_18863"},
 {
 "persName":
 "Virginia Mandyczewski",
 "ref":
 "person_17829"}],
 "listBibl":
  [
 {
 "title":
 "Reigen. Zehn Dialoge",
 "ref":
 "pmb29855"}
 ,  {
 "title":
 "Im Spiel der Sommerl체fte. In drei Aufz체gen",
 "ref":
 "pmb30945"}
 ],
 "listPlace":
  [
 {
 "placeName":
 "IV., Wieden",
 "ref":
 "pmb54"}
 ,  {
 "placeName":
 "Prag",
 "ref":
 "pmb652"}
 ]
}
}, {
 "type":
 "schnitzler-orte",
 "color":
 "#045344",
 "caption":
 "Aufenthaltsorte",
 "head":
 "Wien",
 "desc":
{"listPlace":
  [
 {
 "placeName":
 "XVIII., W채hring",
 "ref":
 ""}
 ,  {
 "placeName":
 "IV., Wieden",
 "ref":
 ""}
 ]
}
}] 