[{
 "type":
 "schnitzler-tagebuch",
 "color":
 "#037a33",
 "filename":
 "entry__1929-07-05",
 "caption":
 "Tagebuch",
 "idno":
 "https://schnitzler-tagebuch.acdh.oeaw.ac.at/entry__1929-07-05.html",
 "head":
 "Tagebuch, 5. Juli 1929",
 "desc":
{"listPerson":
  [
{
 "persName":
 "Ferdinand Donath",
 "ref":
 "person_14482"},
 {
 "persName":
 "Anna Eisenmenger",
 "ref":
 "person_14682"},
 {
 "persName":
 "Else Kraus",
 "ref":
 "person_17106"},
 {
 "persName":
 "Emma Beatrice Marshall",
 "ref":
 "person_17933"},
 {
 "persName":
 "Clara Katharina Pollaczek",
 "ref":
 "person_18863"},
 {
 "persName":
 "Hans Schnitzler",
 "ref":
 "person_19821"},
 {
 "persName":
 "Helene Schnitzler",
 "ref":
 "person_19823"},
 {
 "persName":
 "Julius Schnitzler",
 "ref":
 "person_19827"},
 {
 "persName":
 "Leopoldine Wertheimer",
 "ref":
 "person_21261"},
 {
 "persName":
 "Anna Donath",
 "ref":
 "person_14481"},
 {
 "persName":
 "Ruth Lindberg",
 "ref":
 "person_17562"},
 {
 "persName":
 "Otto Paul Schinnerer",
 "ref":
 "person_19704"}],
 "listBibl":
  [
 {
 "title":
 "Im Spiel der Sommerlüfte. In drei Aufzügen",
 "ref":
 "pmb30945"}
 ,  {
 "title":
 "Zug der Schatten",
 "ref":
 "pmb32049"}
 ]
}
}, {
 "type":
 "schnitzler-orte",
 "color":
 "#045344",
 "caption":
 "Aufenthaltsorte",
 "head":
 "Wien",
 "desc":
{"listPlace":
  [
 {
 "placeName":
 "XVIII., Währing",
 "ref":
 ""}
 ]
}
}, {
 "type":
 "pollaczek",
 "color":
 "#1e81b0",
 "filename":
 "ckp707",
 "caption":
 "Pollaczek: Schnitzler und ich",
 "idno":
 "https://pollaczek.acdh.oeaw.ac.at/ckp707.html",
 "head":
 "Tagebuch von Clara Katharina Pollaczek, 4. Juli 1929 – 11. Juli 1929"
}, {
 "type":
 "schnitzler-kempny-buch",
 "subtype":
 "#ISBN3-499-154-57-9",
 "color":
 "#7B3F00",
 "caption":
 "Kempny Tagebuch",
 "head":
 "Hedy Kempny, Tagebucheintrag vom 5. Juli 1929",
 "source":
 "Hedy Kempny und Arthur Schnitzler: Das Mädchen mit den dreizehn Seelen. Eine Korrespondenz ergänzt durch Blätter aus Hedy Kempnys Tagebuch sowie durch eine Auswahl ihrer Erzählungen. Hg. v. Heinz P. Adamek. Reinbek bei Hamburg: Rowohlt 1984. (Neue Frau)"
}] 